README.md
setup.py
s3kv/__init__.py
s3kv/s3kv.py
s3kv.egg-info/PKG-INFO
s3kv.egg-info/SOURCES.txt
s3kv.egg-info/dependency_links.txt
s3kv.egg-info/requires.txt
s3kv.egg-info/top_level.txt