Metadata-Version: 2.1
Name: s3kv
Version: 0.1.5
Summary: A Python library for interacting with S3 key-value store
Home-page: https://github.com/BalLab/s3kv
Author: Balaji Bal
License: UNKNOWN
Platform: UNKNOWN
Classifier: License :: OSI Approved :: MIT License
Classifier: Programming Language :: Python
Classifier: Programming Language :: Python :: 3
Classifier: Programming Language :: Python :: 3.6
Classifier: Programming Language :: Python :: 3.7
Classifier: Programming Language :: Python :: 3.8
Classifier: Programming Language :: Python :: 3.9
